yamlconf/__init__.py
yamlconf/config.py
yamlconf/exceptions.py
yamlconf/utils.py
yamlconf/tests/__init__.py
yamlconf/tests/test_config.py
yamlconf/tests/test_utils.py
yaml_config-0.1.5.dist-info/LICENSE
yaml_config-0.1.5.dist-info/METADATA
yaml_config-0.1.5.dist-info/WHEEL
yaml_config-0.1.5.dist-info/top_level.txt
yaml_config-0.1.5.dist-info/RECORD
